{"paths": {"admin/js/vendor/select2/i18n/af.js": "admin/js/vendor/select2/i18n/af.4f6fcd73488c.js", "admin/js/vendor/select2/i18n/ar.js": "admin/js/vendor/select2/i18n/ar.65aa8e36bf5d.js", "admin/js/vendor/select2/i18n/az.js": "admin/js/vendor/select2/i18n/az.270c257daf81.js", "admin/js/vendor/select2/i18n/bg.js": "admin/js/vendor/select2/i18n/bg.39b8be30d4f0.js", "admin/js/vendor/select2/i18n/bn.js": "admin/js/vendor/select2/i18n/bn.6d42b4dd5665.js", "admin/js/vendor/select2/i18n/bs.js": "admin/js/vendor/select2/i18n/bs.91624382358e.js", "admin/js/vendor/select2/i18n/ca.js": "admin/js/vendor/select2/i18n/ca.a166b745933a.js", "admin/js/vendor/select2/i18n/cs.js": "admin/js/vendor/select2/i18n/cs.4f43e8e7d33a.js", "admin/js/vendor/select2/i18n/da.js": "admin/js/vendor/select2/i18n/da.766346afe4dd.js", "admin/js/vendor/select2/i18n/de.js": "admin/js/vendor/select2/i18n/de.8a1c222b0204.js", "admin/js/vendor/select2/i18n/dsb.js": "admin/js/vendor/select2/i18n/dsb.56372c92d2f1.js", "admin/js/vendor/select2/i18n/el.js": "admin/js/vendor/select2/i18n/el.27097f071856.js", "admin/js/vendor/select2/i18n/en.js": "admin/js/vendor/select2/i18n/en.cf932ba09a98.js", "admin/js/vendor/select2/i18n/es.js": "admin/js/vendor/select2/i18n/es.66dbc2652fb1.js", "admin/js/vendor/select2/i18n/et.js": "admin/js/vendor/select2/i18n/et.2b96fd98289d.js", "admin/js/vendor/select2/i18n/eu.js": "admin/js/vendor/select2/i18n/eu.adfe5c97b72c.js", "admin/js/vendor/select2/i18n/fa.js": "admin/js/vendor/select2/i18n/fa.3b5bd1961cfd.js", "admin/js/vendor/select2/i18n/fi.js": "admin/js/vendor/select2/i18n/fi.614ec42aa9ba.js", "admin/js/vendor/select2/i18n/fr.js": "admin/js/vendor/select2/i18n/fr.05e0542fcfe6.js", "admin/js/vendor/select2/i18n/gl.js": "admin/js/vendor/select2/i18n/gl.d99b1fedaa86.js", "admin/js/vendor/select2/i18n/he.js": "admin/js/vendor/select2/i18n/he.e420ff6cd3ed.js", "admin/js/vendor/select2/i18n/hi.js": "admin/js/vendor/select2/i18n/hi.70640d41628f.js", "admin/js/vendor/select2/i18n/hr.js": "admin/js/vendor/select2/i18n/hr.a2b092cc1147.js", "admin/js/vendor/select2/i18n/hsb.js": "admin/js/vendor/select2/i18n/hsb.fa3b55265efe.js", "admin/js/vendor/select2/i18n/hu.js": "admin/js/vendor/select2/i18n/hu.6ec6039cb8a3.js", "admin/js/vendor/select2/i18n/hy.js": "admin/js/vendor/select2/i18n/hy.c7babaeef5a6.js", "admin/js/vendor/select2/i18n/id.js": "admin/js/vendor/select2/i18n/id.04debded514d.js", "admin/js/vendor/select2/i18n/is.js": "admin/js/vendor/select2/i18n/is.3ddd9a6a97e9.js", "admin/js/vendor/select2/i18n/it.js": "admin/js/vendor/select2/i18n/it.be4fe8d365b5.js", "admin/js/vendor/select2/i18n/ja.js": "admin/js/vendor/select2/i18n/ja.170ae885d74f.js", "admin/js/vendor/select2/i18n/ka.js": "admin/js/vendor/select2/i18n/ka.2083264a54f0.js", "admin/js/vendor/select2/i18n/km.js": "admin/js/vendor/select2/i18n/km.c23089cb06ca.js", "admin/js/vendor/select2/i18n/ko.js": "admin/js/vendor/select2/i18n/ko.e7be6c20e673.js", "admin/js/vendor/select2/i18n/lt.js": "admin/js/vendor/select2/i18n/lt.23c7ce903300.js", "admin/js/vendor/select2/i18n/lv.js": "admin/js/vendor/select2/i18n/lv.08e62128eac1.js", "admin/js/vendor/select2/i18n/mk.js": "admin/js/vendor/select2/i18n/mk.dabbb9087130.js", "admin/js/vendor/select2/i18n/ms.js": "admin/js/vendor/select2/i18n/ms.4ba82c9a51ce.js", "admin/js/vendor/select2/i18n/nb.js": "admin/js/vendor/select2/i18n/nb.da2fce143f27.js", "admin/js/vendor/select2/i18n/ne.js": "admin/js/vendor/select2/i18n/ne.3d79fd3f08db.js", "admin/js/vendor/select2/i18n/nl.js": "admin/js/vendor/select2/i18n/nl.997868a37ed8.js", "admin/js/vendor/select2/i18n/pl.js": "admin/js/vendor/select2/i18n/pl.6031b4f16452.js", "admin/js/vendor/select2/i18n/ps.js": "admin/js/vendor/select2/i18n/ps.38dfa47af9e0.js", "admin/js/vendor/select2/i18n/pt-BR.js": "admin/js/vendor/select2/i18n/pt-BR.e1b294433e7f.js", "admin/js/vendor/select2/i18n/pt.js": "admin/js/vendor/select2/i18n/pt.33b4a3b44d43.js", "admin/js/vendor/select2/i18n/ro.js": "admin/js/vendor/select2/i18n/ro.f75cb460ec3b.js", "admin/js/vendor/select2/i18n/ru.js": "admin/js/vendor/select2/i18n/ru.934aa95f5b5f.js", "admin/js/vendor/select2/i18n/sk.js": "admin/js/vendor/select2/i18n/sk.33d02cef8d11.js", "admin/js/vendor/select2/i18n/sl.js": "admin/js/vendor/select2/i18n/sl.131a78bc0752.js", "admin/js/vendor/select2/i18n/sq.js": "admin/js/vendor/select2/i18n/sq.5636b60d29c9.js", "admin/js/vendor/select2/i18n/sr-Cyrl.js": "admin/js/vendor/select2/i18n/sr-Cyrl.f254bb8c4c7c.js", "admin/js/vendor/select2/i18n/sr.js": "admin/js/vendor/select2/i18n/sr.5ed85a48f483.js", "admin/js/vendor/select2/i18n/sv.js": "admin/js/vendor/select2/i18n/sv.7a9c2f71e777.js", "admin/js/vendor/select2/i18n/th.js": "admin/js/vendor/select2/i18n/th.f38c20b0221b.js", "admin/js/vendor/select2/i18n/tk.js": "admin/js/vendor/select2/i18n/tk.7c572a68c78f.js", "admin/js/vendor/select2/i18n/tr.js": "admin/js/vendor/select2/i18n/tr.b5a0643d1545.js", "admin/js/vendor/select2/i18n/uk.js": "admin/js/vendor/select2/i18n/uk.8cede7f4803c.js", "admin/js/vendor/select2/i18n/vi.js": "admin/js/vendor/select2/i18n/vi.097a5b75b3e1.js", "admin/js/vendor/select2/i18n/zh-CN.js": "admin/js/vendor/select2/i18n/zh-CN.2cff662ec5f9.js", "admin/js/vendor/select2/i18n/zh-TW.js": "admin/js/vendor/select2/i18n/zh-TW.04554a227c2b.js", "vendor/jqueryui/external/jquery/jquery.js": "vendor/jqueryui/external/jquery/jquery.fb2d334dabf4.js", "admin/css/vendor/select2/LICENSE-SELECT2.md": "admin\\css\\vendor\\select2\\LICENSE-SELECT2.f94142512c91.md", "admin/css/vendor/select2/select2.css": "admin/css/vendor/select2/select2.a2194c262648.css", "admin/css/vendor/select2/select2.min.css": "admin/css/vendor/select2/select2.min.9f54e6414f87.css", "admin/js/vendor/jquery/jquery.js": "admin/js/vendor/jquery/jquery.2849239b95f5.js", "admin/js/vendor/jquery/jquery.min.js": "admin/js/vendor/jquery/jquery.min.8fb8fee4fcc3.js", "admin/js/vendor/jquery/LICENSE.txt": "admin\\js\\vendor\\jquery\\LICENSE.de877aa6d744.txt", "admin/js/vendor/select2/LICENSE.md": "admin\\js\\vendor\\select2\\LICENSE.f94142512c91.md", "admin/js/vendor/select2/select2.full.js": "admin/js/vendor/select2/select2.full.c2afdeda3058.js", "admin/js/vendor/select2/select2.full.min.js": "admin/js/vendor/select2/select2.full.min.fcd7500d8e13.js", "admin/js/vendor/xregexp/LICENSE.txt": "admin\\js\\vendor\\xregexp\\LICENSE.bf79e414957a.txt", "admin/js/vendor/xregexp/xregexp.js": "admin/js/vendor/xregexp/xregexp.efda034b9537.js", "admin/js/vendor/xregexp/xregexp.min.js": "admin/js/vendor/xregexp/xregexp.min.b0439563a5d3.js", "scss/argon-dashboard/bootstrap/forms/_floating-labels.scss": "scss\\argon-dashboard\\bootstrap\\forms\\_floating-labels.2cfb227e92e8.scss", "scss/argon-dashboard/bootstrap/forms/_form-check.scss": "scss\\argon-dashboard\\bootstrap\\forms\\_form-check.d04cb24995e8.scss", "scss/argon-dashboard/bootstrap/forms/_form-control.scss": "scss\\argon-dashboard\\bootstrap\\forms\\_form-control.f948cf8b1b3b.scss", "scss/argon-dashboard/bootstrap/forms/_form-range.scss": "scss\\argon-dashboard\\bootstrap\\forms\\_form-range.add1beeff703.scss", "scss/argon-dashboard/bootstrap/forms/_form-select.scss": "scss\\argon-dashboard\\bootstrap\\forms\\_form-select.befbda38e548.scss", "scss/argon-dashboard/bootstrap/forms/_form-text.scss": "scss\\argon-dashboard\\bootstrap\\forms\\_form-text.3c18d8708d34.scss", "scss/argon-dashboard/bootstrap/forms/_input-group.scss": "scss\\argon-dashboard\\bootstrap\\forms\\_input-group.89c79d20b83b.scss", "scss/argon-dashboard/bootstrap/forms/_labels.scss": "scss\\argon-dashboard\\bootstrap\\forms\\_labels.5cebf4f019f4.scss", "scss/argon-dashboard/bootstrap/forms/_validation.scss": "scss\\argon-dashboard\\bootstrap\\forms\\_validation.2a11a9255e11.scss", "scss/argon-dashboard/bootstrap/helpers/_clearfix.scss": "scss\\argon-dashboard\\bootstrap\\helpers\\_clearfix.01ed6cc70519.scss", "scss/argon-dashboard/bootstrap/helpers/_colored-links.scss": "scss\\argon-dashboard\\bootstrap\\helpers\\_colored-links.06e8cdfe3d92.scss", "scss/argon-dashboard/bootstrap/helpers/_position.scss": "scss\\argon-dashboard\\bootstrap\\helpers\\_position.7a8080dca11e.scss", "scss/argon-dashboard/bootstrap/helpers/_ratio.scss": "scss\\argon-dashboard\\bootstrap\\helpers\\_ratio.61857698ee98.scss", "scss/argon-dashboard/bootstrap/helpers/_stacks.scss": "scss\\argon-dashboard\\bootstrap\\helpers\\_stacks.27048f226914.scss", "scss/argon-dashboard/bootstrap/helpers/_stretched-link.scss": "scss\\argon-dashboard\\bootstrap\\helpers\\_stretched-link.1cd3650187aa.scss", "scss/argon-dashboard/bootstrap/helpers/_text-truncation.scss": "scss\\argon-dashboard\\bootstrap\\helpers\\_text-truncation.7b3965903a33.scss", "scss/argon-dashboard/bootstrap/helpers/_visually-hidden.scss": "scss\\argon-dashboard\\bootstrap\\helpers\\_visually-hidden.9b5a75ecdb00.scss", "scss/argon-dashboard/bootstrap/helpers/_vr.scss": "scss\\argon-dashboard\\bootstrap\\helpers\\_vr.f32f4021240d.scss", "scss/argon-dashboard/bootstrap/mixins/_alert.scss": "scss\\argon-dashboard\\bootstrap\\mixins\\_alert.77d50cf55468.scss", "scss/argon-dashboard/bootstrap/mixins/_backdrop.scss": "scss\\argon-dashboard\\bootstrap\\mixins\\_backdrop.9adb943f99eb.scss", "scss/argon-dashboard/bootstrap/mixins/_border-radius.scss": "scss\\argon-dashboard\\bootstrap\\mixins\\_border-radius.9365ecee7a6a.scss", "scss/argon-dashboard/bootstrap/mixins/_box-shadow.scss": "scss\\argon-dashboard\\bootstrap\\mixins\\_box-shadow.f5a7d5f8d547.scss", "scss/argon-dashboard/bootstrap/mixins/_breakpoints.scss": "scss\\argon-dashboard\\bootstrap\\mixins\\_breakpoints.9629bb2c04b4.scss", "scss/argon-dashboard/bootstrap/mixins/_buttons.scss": "scss\\argon-dashboard\\bootstrap\\mixins\\_buttons.14962505ec45.scss", "scss/argon-dashboard/bootstrap/mixins/_caret.scss": "scss\\argon-dashboard\\bootstrap\\mixins\\_caret.723bafe1d9ff.scss", "scss/argon-dashboard/bootstrap/mixins/_clearfix.scss": "scss\\argon-dashboard\\bootstrap\\mixins\\_clearfix.101843d44d8f.scss", "scss/argon-dashboard/bootstrap/mixins/_color-scheme.scss": "scss\\argon-dashboard\\bootstrap\\mixins\\_color-scheme.6f3cb289c06a.scss", "scss/argon-dashboard/bootstrap/mixins/_container.scss": "scss\\argon-dashboard\\bootstrap\\mixins\\_container.81153f825e19.scss", "scss/argon-dashboard/bootstrap/mixins/_deprecate.scss": "scss\\argon-dashboard\\bootstrap\\mixins\\_deprecate.198564417395.scss", "scss/argon-dashboard/bootstrap/mixins/_forms.scss": "scss\\argon-dashboard\\bootstrap\\mixins\\_forms.be8a374ed878.scss", "scss/argon-dashboard/bootstrap/mixins/_gradients.scss": "scss\\argon-dashboard\\bootstrap\\mixins\\_gradients.98e3a535b741.scss", "scss/argon-dashboard/bootstrap/mixins/_grid.scss": "scss\\argon-dashboard\\bootstrap\\mixins\\_grid.0ec027903670.scss", "scss/argon-dashboard/bootstrap/mixins/_image.scss": "scss\\argon-dashboard\\bootstrap\\mixins\\_image.4be5005673c8.scss", "scss/argon-dashboard/bootstrap/mixins/_list-group.scss": "scss\\argon-dashboard\\bootstrap\\mixins\\_list-group.f9539c99a853.scss", "scss/argon-dashboard/bootstrap/mixins/_lists.scss": "scss\\argon-dashboard\\bootstrap\\mixins\\_lists.c7e34a356a86.scss", "scss/argon-dashboard/bootstrap/mixins/_pagination.scss": "scss\\argon-dashboard\\bootstrap\\mixins\\_pagination.597271023445.scss", "scss/argon-dashboard/bootstrap/mixins/_reset-text.scss": "scss\\argon-dashboard\\bootstrap\\mixins\\_reset-text.9ec95074e21f.scss", "scss/argon-dashboard/bootstrap/mixins/_resize.scss": "scss\\argon-dashboard\\bootstrap\\mixins\\_resize.af032cea5fd5.scss", "scss/argon-dashboard/bootstrap/mixins/_table-variants.scss": "scss\\argon-dashboard\\bootstrap\\mixins\\_table-variants.cee8035523af.scss", "scss/argon-dashboard/bootstrap/mixins/_text-truncate.scss": "scss\\argon-dashboard\\bootstrap\\mixins\\_text-truncate.c51a1018bf42.scss", "scss/argon-dashboard/bootstrap/mixins/_transition.scss": "scss\\argon-dashboard\\bootstrap\\mixins\\_transition.80dea9aa5861.scss", "scss/argon-dashboard/bootstrap/mixins/_utilities.scss": "scss\\argon-dashboard\\bootstrap\\mixins\\_utilities.347c0a56e8ac.scss", "scss/argon-dashboard/bootstrap/mixins/_visually-hidden.scss": "scss\\argon-dashboard\\bootstrap\\mixins\\_visually-hidden.df3bbdea4142.scss", "scss/argon-dashboard/bootstrap/utilities/_api.scss": "scss\\argon-dashboard\\bootstrap\\utilities\\_api.2c049eea7857.scss", "scss/argon-dashboard/bootstrap/vendor/_rfs.scss": "scss\\argon-dashboard\\bootstrap\\vendor\\_rfs.e39df45a0fc1.scss", "scss/argon-dashboard/plugins/free/plugins.scss": "scss\\argon-dashboard\\plugins\\free\\plugins.78b69afa2f71.scss", "scss/argon-dashboard/plugins/free/_flatpickr.scss": "scss\\argon-dashboard\\plugins\\free\\_flatpickr.44e93649891f.scss", "scss/argon-dashboard/plugins/free/_nouislider.scss": "scss\\argon-dashboard\\plugins\\free\\_nouislider.639d58266305.scss", "scss/argon-dashboard/plugins/free/_perfect-scrollbar.scss": "scss\\argon-dashboard\\plugins\\free\\_perfect-scrollbar.6f36b1309fbb.scss", "scss/argon-dashboard/plugins/free/_prism.scss": "scss\\argon-dashboard\\plugins\\free\\_prism.7a010abe78da.scss", "fonts/font-awesome-4.7.0/css/font-awesome.css": "fonts/font-awesome-4.7.0/css/font-awesome.7d46203b9170.css", "fonts/font-awesome-4.7.0/css/font-awesome.min.css": "fonts/font-awesome-4.7.0/css/font-awesome.min.bf0c425cdb73.css", "fonts/font-awesome-4.7.0/fonts/fontawesome-webfont.eot": "fonts\\font-awesome-4.7.0\\fonts\\fontawesome-webfont.674f50d287a8.eot", "fonts/font-awesome-4.7.0/fonts/fontawesome-webfont.svg": "fonts\\font-awesome-4.7.0\\fonts\\fontawesome-webfont.912ec66d7572.svg", "fonts/font-awesome-4.7.0/fonts/fontawesome-webfont.ttf": "fonts\\font-awesome-4.7.0\\fonts\\fontawesome-webfont.b06871f281fe.ttf", "fonts/font-awesome-4.7.0/fonts/fontawesome-webfont.woff": "fonts\\font-awesome-4.7.0\\fonts\\fontawesome-webfont.fee66e712a8a.woff", "fonts/font-awesome-4.7.0/fonts/fontawesome-webfont.woff2": "fonts\\font-awesome-4.7.0\\fonts\\fontawesome-webfont.af7ae505a9ee.woff2", "fonts/font-awesome-4.7.0/fonts/FontAwesome.otf": "fonts\\font-awesome-4.7.0\\fonts\\FontAwesome.0d2717cd5d85.otf", "fonts/font-awesome-4.7.0/less/animated.less": "fonts\\font-awesome-4.7.0\\less\\animated.08baef05e053.less", "fonts/font-awesome-4.7.0/less/bordered-pulled.less": "fonts\\font-awesome-4.7.0\\less\\bordered-pulled.898f90e40876.less", "fonts/font-awesome-4.7.0/less/core.less": "fonts\\font-awesome-4.7.0\\less\\core.fb4efe4ae637.less", "fonts/font-awesome-4.7.0/less/fixed-width.less": "fonts\\font-awesome-4.7.0\\less\\fixed-width.5e07ec001f8d.less", "fonts/font-awesome-4.7.0/less/font-awesome.less": "fonts\\font-awesome-4.7.0\\less\\font-awesome.15cb7faa0243.less", "fonts/font-awesome-4.7.0/less/icons.less": "fonts\\font-awesome-4.7.0\\less\\icons.bf95b901c36b.less", "fonts/font-awesome-4.7.0/less/larger.less": "fonts\\font-awesome-4.7.0\\less\\larger.8cb65280c0f8.less", "fonts/font-awesome-4.7.0/less/list.less": "fonts\\font-awesome-4.7.0\\less\\list.975571323cf8.less", "fonts/font-awesome-4.7.0/less/mixins.less": "fonts\\font-awesome-4.7.0\\less\\mixins.fbb1f2f1ab96.less", "fonts/font-awesome-4.7.0/less/path.less": "fonts\\font-awesome-4.7.0\\less\\path.a8c41460c42a.less", "fonts/font-awesome-4.7.0/less/rotated-flipped.less": "fonts\\font-awesome-4.7.0\\less\\rotated-flipped.a8476cdc50c2.less", "fonts/font-awesome-4.7.0/less/screen-reader.less": "fonts\\font-awesome-4.7.0\\less\\screen-reader.0f8816172645.less", "fonts/font-awesome-4.7.0/less/stacked.less": "fonts\\font-awesome-4.7.0\\less\\stacked.518e2b2d2639.less", "fonts/font-awesome-4.7.0/less/variables.less": "fonts\\font-awesome-4.7.0\\less\\variables.be3f6eed38aa.less", "fonts/font-awesome-4.7.0/scss/font-awesome.scss": "fonts\\font-awesome-4.7.0\\scss\\font-awesome.8c015559216d.scss", "fonts/font-awesome-4.7.0/scss/_animated.scss": "fonts\\font-awesome-4.7.0\\scss\\_animated.39ff4f359a7b.scss", "fonts/font-awesome-4.7.0/scss/_bordered-pulled.scss": "fonts\\font-awesome-4.7.0\\scss\\_bordered-pulled.4cad0df17bf4.scss", "fonts/font-awesome-4.7.0/scss/_core.scss": "fonts\\font-awesome-4.7.0\\scss\\_core.ef059a98cf9d.scss", "fonts/font-awesome-4.7.0/scss/_fixed-width.scss": "fonts\\font-awesome-4.7.0\\scss\\_fixed-width.9277ab6964a4.scss", "fonts/font-awesome-4.7.0/scss/_icons.scss": "fonts\\font-awesome-4.7.0\\scss\\_icons.de9fa842ad0b.scss", "fonts/font-awesome-4.7.0/scss/_larger.scss": "fonts\\font-awesome-4.7.0\\scss\\_larger.e95931566f6f.scss", "fonts/font-awesome-4.7.0/scss/_list.scss": "fonts\\font-awesome-4.7.0\\scss\\_list.7107e80b0539.scss", "fonts/font-awesome-4.7.0/scss/_mixins.scss": "fonts\\font-awesome-4.7.0\\scss\\_mixins.aa2b8f32b403.scss", "fonts/font-awesome-4.7.0/scss/_path.scss": "fonts\\font-awesome-4.7.0\\scss\\_path.ab5a9e838856.scss", "fonts/font-awesome-4.7.0/scss/_rotated-flipped.scss": "fonts\\font-awesome-4.7.0\\scss\\_rotated-flipped.9f5d4bc6fade.scss", "fonts/font-awesome-4.7.0/scss/_screen-reader.scss": "fonts\\font-awesome-4.7.0\\scss\\_screen-reader.8907bd7dbf47.scss", "fonts/font-awesome-4.7.0/scss/_stacked.scss": "fonts\\font-awesome-4.7.0\\scss\\_stacked.5594237226ae.scss", "fonts/font-awesome-4.7.0/scss/_variables.scss": "fonts\\font-awesome-4.7.0\\scss\\_variables.dc5261f37a8a.scss", "fonts/iconic/css/material-design-iconic-font.css": "fonts/iconic/css/material-design-iconic-font.6f505f6af6e3.css", "fonts/iconic/css/material-design-iconic-font.min.css": "fonts/iconic/css/material-design-iconic-font.min.1bbb03fb6fd3.css", "fonts/iconic/fonts/Material-Design-Iconic-Font.eot": "fonts\\iconic\\fonts\\Material-Design-Iconic-Font.e833b2e24712.eot", "fonts/iconic/fonts/Material-Design-Iconic-Font.svg": "fonts\\iconic\\fonts\\Material-Design-Iconic-Font.230faa5f470e.svg", "fonts/iconic/fonts/Material-Design-Iconic-Font.ttf": "fonts\\iconic\\fonts\\Material-Design-Iconic-Font.b351bd62abcd.ttf", "fonts/iconic/fonts/Material-Design-Iconic-Font.woff": "fonts\\iconic\\fonts\\Material-Design-Iconic-Font.d2a55d331bdd.woff", "fonts/iconic/fonts/Material-Design-Iconic-Font.woff2": "fonts\\iconic\\fonts\\Material-Design-Iconic-Font.a4d31128b633.woff2", "fonts/linearicons-v1.0.0/WebFont/Linearicons-Free.eot": "fonts\\linearicons-v1.0.0\\WebFont\\Linearicons-Free.b9b7f23cb61b.eot", "fonts/linearicons-v1.0.0/WebFont/Linearicons-Free.svg": "fonts\\linearicons-v1.0.0\\WebFont\\Linearicons-Free.2781bf543c08.svg", "fonts/linearicons-v1.0.0/WebFont/Linearicons-Free.ttf": "fonts\\linearicons-v1.0.0\\WebFont\\Linearicons-Free.2f3e9f80fff7.ttf", "fonts/linearicons-v1.0.0/WebFont/Linearicons-Free.woff": "fonts\\linearicons-v1.0.0\\WebFont\\Linearicons-Free.65060723fe96.woff", "fonts/linearicons-v1.0.0/WebFont/Linearicons-Free.woff2": "fonts\\linearicons-v1.0.0\\WebFont\\Linearicons-Free.03e91f122aa5.woff2", "vendor/animsition/css/animsition.css": "vendor/animsition/css/animsition.bcdc8e7a8737.css", "vendor/animsition/css/animsition.min.css": "vendor/animsition/css/animsition.min.312fbe26010f.css", "vendor/animsition/js/animsition.js": "vendor/animsition/js/animsition.1ee319899bc4.js", "vendor/animsition/js/animsition.min.js": "vendor/animsition/js/animsition.min.72d24e37ce24.js", "vendor/bootstrap/css/bootstrap-grid.css": "vendor/bootstrap/css/bootstrap-grid.68dba5af0b67.css", "vendor/bootstrap/css/bootstrap-grid.css.map": "vendor\\bootstrap\\css\\bootstrap-grid.css.fc60e0b490ec.map", "vendor/bootstrap/css/bootstrap-grid.min.css": "vendor/bootstrap/css/bootstrap-grid.min.81ac95ea7a4a.css", "vendor/bootstrap/css/bootstrap-grid.min.css.map": "vendor\\bootstrap\\css\\bootstrap-grid.min.css.94ffff228ac3.map", "vendor/bootstrap/css/bootstrap-reboot.css": "vendor/bootstrap/css/bootstrap-reboot.300fc510017f.css", "vendor/bootstrap/css/bootstrap-reboot.css.map": "vendor\\bootstrap\\css\\bootstrap-reboot.css.2d191e244cc6.map", "vendor/bootstrap/css/bootstrap-reboot.min.css": "vendor/bootstrap/css/bootstrap-reboot.min.28ed2bcac518.css", "vendor/bootstrap/css/bootstrap-reboot.min.css.map": "vendor\\bootstrap\\css\\bootstrap-reboot.min.css.f6c26739b466.map", "vendor/bootstrap/css/bootstrap.css": "vendor/bootstrap/css/bootstrap.afee1b42daf2.css", "vendor/bootstrap/css/bootstrap.css.map": "vendor\\bootstrap\\css\\bootstrap.css.0df0f86ed6e6.map", "vendor/bootstrap/css/bootstrap.min.css": "vendor/bootstrap/css/bootstrap.min.3ffbab350748.css", "vendor/bootstrap/css/bootstrap.min.css.map": "vendor\\bootstrap\\css\\bootstrap.min.css.7b85d321f585.map", "vendor/bootstrap/js/bootstrap.js": "vendor/bootstrap/js/bootstrap.23a49d81e87a.js", "vendor/bootstrap/js/bootstrap.min.js": "vendor/bootstrap/js/bootstrap.min.baaadea4492b.js", "vendor/bootstrap/js/popper.js": "vendor/bootstrap/js/popper.0fee5ec14593.js", "vendor/bootstrap/js/popper.min.js": "vendor/bootstrap/js/popper.min.3601694e7b48.js", "vendor/bootstrap/js/tooltip.js": "vendor/bootstrap/js/tooltip.2222056172a4.js", "vendor/jqueryui/images/ui-icons_444444_256x240.png": "vendor\\jqueryui\\images\\ui-icons_444444_256x240.d10bc07005bb.png", "vendor/jqueryui/images/ui-icons_555555_256x240.png": "vendor\\jqueryui\\images\\ui-icons_555555_256x240.00dd0ec0a16a.png", "vendor/jqueryui/images/ui-icons_777620_256x240.png": "vendor\\jqueryui\\images\\ui-icons_777620_256x240.4e7e3e142f39.png", "vendor/jqueryui/images/ui-icons_777777_256x240.png": "vendor\\jqueryui\\images\\ui-icons_777777_256x240.40bf25799e4f.png", "vendor/jqueryui/images/ui-icons_cc0000_256x240.png": "vendor\\jqueryui\\images\\ui-icons_cc0000_256x240.093a81913827.png", "vendor/jqueryui/images/ui-icons_ffffff_256x240.png": "vendor\\jqueryui\\images\\ui-icons_ffffff_256x240.ea4ebe072be7.png", "vendor/lightbox2/css/lightbox.css": "vendor/lightbox2/css/lightbox.aeff4200b4f6.css", "vendor/lightbox2/css/lightbox.min.css": "vendor/lightbox2/css/lightbox.min.15d8bdaa9985.css", "vendor/lightbox2/images/close.png": "vendor\\lightbox2\\images\\close.d9d2d0b1308c.png", "vendor/lightbox2/images/loading.gif": "vendor\\lightbox2\\images\\loading.2299ad0b3f63.gif", "vendor/lightbox2/images/next.png": "vendor\\lightbox2\\images\\next.31f15875975a.png", "vendor/lightbox2/images/prev.png": "vendor\\lightbox2\\images\\prev.84b76dee6b27.png", "vendor/lightbox2/js/lightbox-plus-jquery.js": "vendor/lightbox2/js/lightbox-plus-jquery.153aee90c7a1.js", "vendor/lightbox2/js/lightbox-plus-jquery.min.js": "vendor/lightbox2/js/lightbox-plus-jquery.min.47e071ff0dd9.js", "vendor/lightbox2/js/lightbox-plus-jquery.min.map": "vendor\\lightbox2\\js\\lightbox-plus-jquery.min.784f11433c53.map", "vendor/lightbox2/js/lightbox.js": "vendor/lightbox2/js/lightbox.b2321d3677fb.js", "vendor/lightbox2/js/lightbox.min.js": "vendor/lightbox2/js/lightbox.min.d1ed8965edbf.js", "vendor/lightbox2/js/lightbox.min.map": "vendor\\lightbox2\\js\\lightbox.min.f53014008f46.map", "vendor/slick/fonts/slick.eot": "vendor\\slick\\fonts\\slick.ced611daf770.eot", "vendor/slick/fonts/slick.svg": "vendor\\slick\\fonts\\slick.f97e3bbf7325.svg", "vendor/slick/fonts/slick.ttf": "vendor\\slick\\fonts\\slick.d41f55a78e6f.ttf", "vendor/slick/fonts/slick.woff": "vendor\\slick\\fonts\\slick.b7c9e1e479de.woff", "admin/img/gis/move_vertex_off.svg": "admin\\img\\gis\\move_vertex_off.7a23bf31ef8a.svg", "admin/img/gis/move_vertex_on.svg": "admin\\img\\gis\\move_vertex_on.0047eba25b67.svg", "admin/js/admin/DateTimeShortcuts.js": "admin/js/admin/DateTimeShortcuts.5548f99471bf.js", "admin/js/admin/RelatedObjectLookups.js": "admin/js/admin/RelatedObjectLookups.b4d76b6aaf0b.js", "img/icons/flags/AU.png": "img\\icons\\flags\\AU.187afd0446a8.png", "img/icons/flags/BR.png": "img\\icons\\flags\\BR.f607bcf1ebf5.png", "img/icons/flags/DE.png": "img\\icons\\flags\\DE.cfdb67379bdf.png", "img/icons/flags/GB.png": "img\\icons\\flags\\GB.6fcd6976734a.png", "img/icons/flags/US.png": "img\\icons\\flags\\US.4ffc0161dd47.png", "scss/argon-dashboard/bootstrap/bootstrap-grid.scss": "scss\\argon-dashboard\\bootstrap\\bootstrap-grid.e17db52dc185.scss", "scss/argon-dashboard/bootstrap/bootstrap-reboot.scss": "scss\\argon-dashboard\\bootstrap\\bootstrap-reboot.5790ab20be38.scss", "scss/argon-dashboard/bootstrap/bootstrap-utilities.scss": "scss\\argon-dashboard\\bootstrap\\bootstrap-utilities.b9fad2c49f43.scss", "scss/argon-dashboard/bootstrap/bootstrap.scss": "scss\\argon-dashboard\\bootstrap\\bootstrap.3f018761d20d.scss", "scss/argon-dashboard/bootstrap/_accordion.scss": "scss\\argon-dashboard\\bootstrap\\_accordion.e884bc1b576e.scss", "scss/argon-dashboard/bootstrap/_alert.scss": "scss\\argon-dashboard\\bootstrap\\_alert.8998dc7d7b3e.scss", "scss/argon-dashboard/bootstrap/_badge.scss": "scss\\argon-dashboard\\bootstrap\\_badge.010407932e86.scss", "scss/argon-dashboard/bootstrap/_breadcrumb.scss": "scss\\argon-dashboard\\bootstrap\\_breadcrumb.5be2578d6dc6.scss", "scss/argon-dashboard/bootstrap/_button-group.scss": "scss\\argon-dashboard\\bootstrap\\_button-group.a41168202c44.scss", "scss/argon-dashboard/bootstrap/_buttons.scss": "scss\\argon-dashboard\\bootstrap\\_buttons.a2b5c1803c6b.scss", "scss/argon-dashboard/bootstrap/_card.scss": "scss\\argon-dashboard\\bootstrap\\_card.712c080ff88a.scss", "scss/argon-dashboard/bootstrap/_carousel.scss": "scss\\argon-dashboard\\bootstrap\\_carousel.3f3c35da07d0.scss", "scss/argon-dashboard/bootstrap/_close.scss": "scss\\argon-dashboard\\bootstrap\\_close.f3eeef2d1971.scss", "scss/argon-dashboard/bootstrap/_containers.scss": "scss\\argon-dashboard\\bootstrap\\_containers.194272731296.scss", "scss/argon-dashboard/bootstrap/_dropdown.scss": "scss\\argon-dashboard\\bootstrap\\_dropdown.a33a6c000a09.scss", "scss/argon-dashboard/bootstrap/_forms.scss": "scss\\argon-dashboard\\bootstrap\\_forms.af9736f55ccf.scss", "scss/argon-dashboard/bootstrap/_functions.scss": "scss\\argon-dashboard\\bootstrap\\_functions.4fb3bb853b76.scss", "scss/argon-dashboard/bootstrap/_grid.scss": "scss\\argon-dashboard\\bootstrap\\_grid.f5825b113cfe.scss", "scss/argon-dashboard/bootstrap/_helpers.scss": "scss\\argon-dashboard\\bootstrap\\_helpers.d2785f3cd7d9.scss", "scss/argon-dashboard/bootstrap/_images.scss": "scss\\argon-dashboard\\bootstrap\\_images.218dcc5eaa6e.scss", "scss/argon-dashboard/bootstrap/_list-group.scss": "scss\\argon-dashboard\\bootstrap\\_list-group.a968ce8d935f.scss", "scss/argon-dashboard/bootstrap/_mixins.scss": "scss\\argon-dashboard\\bootstrap\\_mixins.a15c6d6bb431.scss", "scss/argon-dashboard/bootstrap/_modal.scss": "scss\\argon-dashboard\\bootstrap\\_modal.0d9708a2f13d.scss", "scss/argon-dashboard/bootstrap/_nav.scss": "scss\\argon-dashboard\\bootstrap\\_nav.2703dfdcd9b7.scss", "scss/argon-dashboard/bootstrap/_navbar.scss": "scss\\argon-dashboard\\bootstrap\\_navbar.f4e669042bf0.scss", "scss/argon-dashboard/bootstrap/_offcanvas.scss": "scss\\argon-dashboard\\bootstrap\\_offcanvas.402bc60076ae.scss", "scss/argon-dashboard/bootstrap/_pagination.scss": "scss\\argon-dashboard\\bootstrap\\_pagination.c1ca597952e3.scss", "scss/argon-dashboard/bootstrap/_placeholders.scss": "scss\\argon-dashboard\\bootstrap\\_placeholders.c94f25e489fd.scss", "scss/argon-dashboard/bootstrap/_popover.scss": "scss\\argon-dashboard\\bootstrap\\_popover.60a87713f98f.scss", "scss/argon-dashboard/bootstrap/_progress.scss": "scss\\argon-dashboard\\bootstrap\\_progress.6705d8e1cf2c.scss", "scss/argon-dashboard/bootstrap/_reboot.scss": "scss\\argon-dashboard\\bootstrap\\_reboot.f9c22fad3ee5.scss", "scss/argon-dashboard/bootstrap/_root.scss": "scss\\argon-dashboard\\bootstrap\\_root.485f6f93aad1.scss", "scss/argon-dashboard/bootstrap/_spinners.scss": "scss\\argon-dashboard\\bootstrap\\_spinners.68d2dbd56727.scss", "scss/argon-dashboard/bootstrap/_tables.scss": "scss\\argon-dashboard\\bootstrap\\_tables.0c40a69244b7.scss", "scss/argon-dashboard/bootstrap/_toasts.scss": "scss\\argon-dashboard\\bootstrap\\_toasts.5dc8ecdf450e.scss", "scss/argon-dashboard/bootstrap/_tooltip.scss": "scss\\argon-dashboard\\bootstrap\\_tooltip.184e4512e7a0.scss", "scss/argon-dashboard/bootstrap/_transitions.scss": "scss\\argon-dashboard\\bootstrap\\_transitions.fe34ff59506f.scss", "scss/argon-dashboard/bootstrap/_type.scss": "scss\\argon-dashboard\\bootstrap\\_type.f71e850c035f.scss", "scss/argon-dashboard/bootstrap/_utilities.scss": "scss\\argon-dashboard\\bootstrap\\_utilities.ec1c79633ace.scss", "scss/argon-dashboard/bootstrap/_variables.scss": "scss\\argon-dashboard\\bootstrap\\_variables.80b08f135914.scss", "scss/argon-dashboard/cards/card-background.scss": "scss\\argon-dashboard\\cards\\card-background.a78b6338940b.scss", "scss/argon-dashboard/cards/card-carousel.scss": "scss\\argon-dashboard\\cards\\card-carousel.3668b3a9be4f.scss", "scss/argon-dashboard/custom/_styles.scss": "scss\\argon-dashboard\\custom\\_styles.d41d8cd98f00.scss", "scss/argon-dashboard/custom/_variables.scss": "scss\\argon-dashboard\\custom\\_variables.d41d8cd98f00.scss", "scss/argon-dashboard/forms/_form-check.scss": "scss\\argon-dashboard\\forms\\_form-check.3b9b7aad5b8b.scss", "scss/argon-dashboard/forms/_form-select.scss": "scss\\argon-dashboard\\forms\\_form-select.96e573d192e5.scss", "scss/argon-dashboard/forms/_form-switch.scss": "scss\\argon-dashboard\\forms\\_form-switch.ed38f6263a30.scss", "scss/argon-dashboard/forms/_forms.scss": "scss\\argon-dashboard\\forms\\_forms.5f05025712bf.scss", "scss/argon-dashboard/forms/_input-group.scss": "scss\\argon-dashboard\\forms\\_input-group.d250aef8221a.scss", "scss/argon-dashboard/forms/_inputs.scss": "scss\\argon-dashboard\\forms\\_inputs.9c65d29e5c1d.scss", "scss/argon-dashboard/forms/_labels.scss": "scss\\argon-dashboard\\forms\\_labels.aa8607eb2e58.scss", "scss/argon-dashboard/mixins/mixins.scss": "scss\\argon-dashboard\\mixins\\mixins.33b4229c9390.scss", "scss/argon-dashboard/mixins/_badge.scss": "scss\\argon-dashboard\\mixins\\_badge.41f975fb69b6.scss", "scss/argon-dashboard/mixins/_colored-shadows.scss": "scss\\argon-dashboard\\mixins\\_colored-shadows.ba8ebe23ca8f.scss", "scss/argon-dashboard/mixins/_hover.scss": "scss\\argon-dashboard\\mixins\\_hover.b1dba03325df.scss", "scss/argon-dashboard/mixins/_social-buttons.scss": "scss\\argon-dashboard\\mixins\\_social-buttons.156796bafe0d.scss", "scss/argon-dashboard/variables/_animations.scss": "scss\\argon-dashboard\\variables\\_animations.6bdb96416f7f.scss", "scss/argon-dashboard/variables/_avatars.scss": "scss\\argon-dashboard\\variables\\_avatars.e6db4cab1432.scss", "scss/argon-dashboard/variables/_badge.scss": "scss\\argon-dashboard\\variables\\_badge.abfc62ee1299.scss", "scss/argon-dashboard/variables/_breadcrumb.scss": "scss\\argon-dashboard\\variables\\_breadcrumb.3b34f4a8c3a0.scss", "scss/argon-dashboard/variables/_cards-extend.scss": "scss\\argon-dashboard\\variables\\_cards-extend.81639cc4f2a7.scss", "scss/argon-dashboard/variables/_cards.scss": "scss\\argon-dashboard\\variables\\_cards.e2cb22f3aa67.scss", "scss/argon-dashboard/variables/_choices.scss": "scss\\argon-dashboard\\variables\\_choices.027e23387de0.scss", "scss/argon-dashboard/variables/_dark-version.scss": "scss\\argon-dashboard\\variables\\_dark-version.36f824a1e16c.scss", "scss/argon-dashboard/variables/_dropdowns.scss": "scss\\argon-dashboard\\variables\\_dropdowns.0ca7d6e1ba92.scss", "scss/argon-dashboard/variables/_fixed-plugin.scss": "scss\\argon-dashboard\\variables\\_fixed-plugin.ddb780936dcd.scss", "scss/argon-dashboard/variables/_form-switch.scss": "scss\\argon-dashboard\\variables\\_form-switch.1128b82771db.scss", "scss/argon-dashboard/variables/_full-calendar.scss": "scss\\argon-dashboard\\variables\\_full-calendar.6574e156c12f.scss", "scss/argon-dashboard/variables/_header.scss": "scss\\argon-dashboard\\variables\\_header.c5c5f0c21b24.scss", "scss/argon-dashboard/variables/_info-areas.scss": "scss\\argon-dashboard\\variables\\_info-areas.39b463f76d56.scss", "scss/argon-dashboard/variables/_misc-extend.scss": "scss\\argon-dashboard\\variables\\_misc-extend.916afce72419.scss", "scss/argon-dashboard/variables/_misc.scss": "scss\\argon-dashboard\\variables\\_misc.780c3b4a9a39.scss", "scss/argon-dashboard/variables/_navbar-vertical.scss": "scss\\argon-dashboard\\variables\\_navbar-vertical.1a5bd6648b38.scss", "scss/argon-dashboard/variables/_navbar.scss": "scss\\argon-dashboard\\variables\\_navbar.4df2d3b5771f.scss", "scss/argon-dashboard/variables/_pagination.scss": "scss\\argon-dashboard\\variables\\_pagination.9d1d958f60ac.scss", "scss/argon-dashboard/variables/_rtl.scss": "scss\\argon-dashboard\\variables\\_rtl.681173651ded.scss", "scss/argon-dashboard/variables/_social-buttons.scss": "scss\\argon-dashboard\\variables\\_social-buttons.b9df0e06256e.scss", "scss/argon-dashboard/variables/_table.scss": "scss\\argon-dashboard\\variables\\_table.cce57bf8a61f.scss", "scss/argon-dashboard/variables/_timeline.scss": "scss\\argon-dashboard\\variables\\_timeline.e8262b2449ba.scss", "scss/argon-dashboard/variables/_utilities-extend.scss": "scss\\argon-dashboard\\variables\\_utilities-extend.207a08ffc6b6.scss", "scss/argon-dashboard/variables/_utilities.scss": "scss\\argon-dashboard\\variables\\_utilities.c008167f5d26.scss", "scss/argon-dashboard/variables/_virtual-reality.scss": "scss\\argon-dashboard\\variables\\_virtual-reality.f58e89bf68f3.scss", "fonts/font-awesome-4.7.0/HELP-US-OUT.txt": "fonts\\font-awesome-4.7.0\\HELP-US-OUT.a1e5be58e81e.txt", "fonts/linearicons-v1.0.0/icon-font.min.css": "fonts/linearicons-v1.0.0/icon-font.min.ec26292e52e5.css", "fonts/Montserrat/Montserrat-Black.ttf": "fonts\\Montserrat\\Montserrat-Black.054ffd1ba6a6.ttf", "fonts/Montserrat/Montserrat-BlackItalic.ttf": "fonts\\Montserrat\\Montserrat-BlackItalic.5811e69d2c09.ttf", "fonts/Montserrat/Montserrat-Bold.ttf": "fonts\\Montserrat\\Montserrat-Bold.a8de8ffe262d.ttf", "fonts/Montserrat/Montserrat-BoldItalic.ttf": "fonts\\Montserrat\\Montserrat-BoldItalic.5de9b5743038.ttf", "fonts/Montserrat/Montserrat-ExtraBold.ttf": "fonts\\Montserrat\\Montserrat-ExtraBold.5e81217f7e14.ttf", "fonts/Montserrat/Montserrat-ExtraBoldItalic.ttf": "fonts\\Montserrat\\Montserrat-ExtraBoldItalic.ae2ace44e8b7.ttf", "fonts/Montserrat/Montserrat-ExtraLight.ttf": "fonts\\Montserrat\\Montserrat-ExtraLight.b415dcea9b37.ttf", "fonts/Montserrat/Montserrat-ExtraLightItalic.ttf": "fonts\\Montserrat\\Montserrat-ExtraLightItalic.d27df57dc92f.ttf", "fonts/Montserrat/Montserrat-Italic.ttf": "fonts\\Montserrat\\Montserrat-Italic.8777b44e5f19.ttf", "fonts/Montserrat/Montserrat-Light.ttf": "fonts\\Montserrat\\Montserrat-Light.9e52b00d7374.ttf", "fonts/Montserrat/Montserrat-LightItalic.ttf": "fonts\\Montserrat\\Montserrat-LightItalic.179eed845298.ttf", "fonts/Montserrat/Montserrat-Medium.ttf": "fonts\\Montserrat\\Montserrat-Medium.5f797490f806.ttf", "fonts/Montserrat/Montserrat-MediumItalic.ttf": "fonts\\Montserrat\\Montserrat-MediumItalic.b74481b36cff.ttf", "fonts/Montserrat/Montserrat-Regular.ttf": "fonts\\Montserrat\\Montserrat-Regular.f7213526ec92.ttf", "fonts/Montserrat/Montserrat-SemiBold.ttf": "fonts\\Montserrat\\Montserrat-SemiBold.31e34a4dc526.ttf", "fonts/Montserrat/Montserrat-SemiBoldItalic.ttf": "fonts\\Montserrat\\Montserrat-SemiBoldItalic.abfff4a0713e.ttf", "fonts/Montserrat/Montserrat-Thin.ttf": "fonts\\Montserrat\\Montserrat-Thin.bbf2ff5d3749.ttf", "fonts/Montserrat/Montserrat-ThinItalic.ttf": "fonts\\Montserrat\\Montserrat-ThinItalic.81fbc5080100.ttf", "fonts/Montserrat/OFL.txt": "fonts\\Montserrat\\OFL.8e4500604642.txt", "fonts/PlayfairDisplay/OFL.txt": "fonts\\PlayfairDisplay\\OFL.2c28fb0a2c4f.txt", "fonts/PlayfairDisplay/PlayfairDisplay-Black.ttf": "fonts\\PlayfairDisplay\\PlayfairDisplay-Black.c319f35d410e.ttf", "fonts/PlayfairDisplay/PlayfairDisplay-BlackItalic.ttf": "fonts\\PlayfairDisplay\\PlayfairDisplay-BlackItalic.ff170d1fc66d.ttf", "fonts/PlayfairDisplay/PlayfairDisplay-Bold.ttf": "fonts\\PlayfairDisplay\\PlayfairDisplay-Bold.07b76bcd33a9.ttf", "fonts/PlayfairDisplay/PlayfairDisplay-BoldItalic.ttf": "fonts\\PlayfairDisplay\\PlayfairDisplay-BoldItalic.b6ed9d8cacae.ttf", "fonts/PlayfairDisplay/PlayfairDisplay-Italic.ttf": "fonts\\PlayfairDisplay\\PlayfairDisplay-Italic.6029087d8c82.ttf", "fonts/PlayfairDisplay/PlayfairDisplay-Regular.ttf": "fonts\\PlayfairDisplay\\PlayfairDisplay-Regular.602025465312.ttf", "fonts/Poppins/Poppins-Black.ttf": "fonts\\Poppins\\Poppins-Black.8971d1710cbf.ttf", "fonts/Poppins/Poppins-BlackItalic.ttf": "fonts\\Poppins\\Poppins-BlackItalic.ad021f07d5d9.ttf", "fonts/Poppins/Poppins-Bold.ttf": "fonts\\Poppins\\Poppins-Bold.7940efc40d8e.ttf", "fonts/Poppins/Poppins-BoldItalic.ttf": "fonts\\Poppins\\Poppins-BoldItalic.0952866304f3.ttf", "fonts/Poppins/Poppins-ExtraBold.ttf": "fonts\\Poppins\\Poppins-ExtraBold.0e6906b2b7be.ttf", "fonts/Poppins/Poppins-ExtraBoldItalic.ttf": "fonts\\Poppins\\Poppins-ExtraBoldItalic.8f1e4e0b5a88.ttf", "fonts/Poppins/Poppins-ExtraLight.ttf": "fonts\\Poppins\\Poppins-ExtraLight.f99f9d50a569.ttf", "fonts/Poppins/Poppins-ExtraLightItalic.ttf": "fonts\\Poppins\\Poppins-ExtraLightItalic.682c805ca8e4.ttf", "fonts/Poppins/Poppins-Italic.ttf": "fonts\\Poppins\\Poppins-Italic.b7e7ed9f2fd6.ttf", "fonts/Poppins/Poppins-Light.ttf": "fonts\\Poppins\\Poppins-Light.3352653dedd5.ttf", "fonts/Poppins/Poppins-LightItalic.ttf": "fonts\\Poppins\\Poppins-LightItalic.f86967072b9e.ttf", "fonts/Poppins/Poppins-Medium.ttf": "fonts\\Poppins\\Poppins-Medium.a4e11dda4053.ttf", "fonts/Poppins/Poppins-MediumItalic.ttf": "fonts\\Poppins\\Poppins-MediumItalic.049c11dc561d.ttf", "fonts/Poppins/Poppins-Regular.ttf": "fonts\\Poppins\\Poppins-Regular.731a28a413d6.ttf", "fonts/Poppins/Poppins-SemiBold.ttf": "fonts\\Poppins\\Poppins-SemiBold.e63b93dfac26.ttf", "fonts/Poppins/Poppins-SemiBoldItalic.ttf": "fonts\\Poppins\\Poppins-SemiBoldItalic.e650e72170e7.ttf", "fonts/Poppins/Poppins-Thin.ttf": "fonts\\Poppins\\Poppins-Thin.735aa7d8e35b.ttf", "fonts/Poppins/Poppins-ThinItalic.ttf": "fonts\\Poppins\\Poppins-ThinItalic.cffb0ae21d03.ttf", "images/icons/favicon.png": "images\\icons\\favicon.1112e0921cd7.png", "images/icons/icon-close.png": "images\\icons\\icon-close.6d254e6311f3.png", "images/icons/icon-close2.png": "images\\icons\\icon-close2.db0c24a04aae.png", "images/icons/icon-email.png": "images\\icons\\icon-email.5a5d5b072d83.png", "images/icons/icon-heart-01.png": "images\\icons\\icon-heart-01.bff3f486c6b2.png", "images/icons/icon-heart-02.png": "images\\icons\\icon-heart-02.e05918ed31e3.png", "images/icons/icon-next.png": "images\\icons\\icon-next.5ad801d98cd4.png", "images/icons/icon-pay-01.png": "images\\icons\\icon-pay-01.e448f9cfda23.png", "images/icons/icon-pay-02.png": "images\\icons\\icon-pay-02.33a57bb96ba5.png", "images/icons/icon-pay-03.png": "images\\icons\\icon-pay-03.f084e2764b7b.png", "images/icons/icon-pay-04.png": "images\\icons\\icon-pay-04.0e67ed569411.png", "images/icons/icon-pay-05.png": "images\\icons\\icon-pay-05.08ced3591c6b.png", "images/icons/icon-prev.png": "images\\icons\\icon-prev.7637c3144bb2.png", "images/icons/logo-01.png": "images\\icons\\logo-01.7f8095fe37e9.png", "images/icons/logo-02.png": "images\\icons\\logo-02.6c16e1c9f347.png", "images/icons/pin.png": "images\\icons\\pin.b53ed7a1dc45.png", "vendor/animate/animate.css": "vendor/animate/animate.57db4a2811f9.css", "vendor/countdowntime/countdowntime.js": "vendor/countdowntime/countdowntime.95d41db2985c.js", "vendor/css-hamburgers/hamburgers.css": "vendor/css-hamburgers/hamburgers.d0b868f3c8ef.css", "vendor/css-hamburgers/hamburgers.min.css": "vendor/css-hamburgers/hamburgers.min.fe22689aadb8.css", "vendor/daterangepicker/daterangepicker.css": "vendor/daterangepicker/daterangepicker.2fba2a36f4a0.css", "vendor/daterangepicker/daterangepicker.js": "vendor/daterangepicker/daterangepicker.17410722717c.js", "vendor/daterangepicker/moment.js": "vendor/daterangepicker/moment.a04210d73e42.js", "vendor/daterangepicker/moment.min.js": "vendor/daterangepicker/moment.min.03c1d3ad0acf.js", "vendor/isotope/isotope.pkgd.min.js": "vendor/isotope/isotope.pkgd.min.39258d5d7a1a.js", "vendor/jquery/jquery-3.2.1.min.js": "vendor/jquery/jquery-3.2.1.min.c9f5aeeca3ad.js", "vendor/jqueryui/index.html": "vendor\\jqueryui\\index.11f31c348968.html", "vendor/jqueryui/jquery-ui.css": "vendor/jqueryui/jquery-ui.2d1c0d46b2fa.css", "vendor/jqueryui/jquery-ui.js": "vendor/jqueryui/jquery-ui.ab5284de5e3d.js", "vendor/jqueryui/jquery-ui.min.css": "vendor/jqueryui/jquery-ui.min.d1de9dd38d6e.css", "vendor/jqueryui/jquery-ui.min.js": "vendor/jqueryui/jquery-ui.min.c15b1008dec3.js", "vendor/jqueryui/jquery-ui.structure.css": "vendor/jqueryui/jquery-ui.structure.b75d9919ded1.css", "vendor/jqueryui/jquery-ui.structure.min.css": "vendor/jqueryui/jquery-ui.structure.min.5581d20aa506.css", "vendor/jqueryui/jquery-ui.theme.css": "vendor/jqueryui/jquery-ui.theme.cb9adfefe608.css", "vendor/jqueryui/jquery-ui.theme.min.css": "vendor/jqueryui/jquery-ui.theme.min.22693c88eb57.css", "vendor/MagnificPopup/jquery.magnific-popup.js": "vendor/MagnificPopup/jquery.magnific-popup.5b23ded83b6a.js", "vendor/MagnificPopup/jquery.magnific-popup.min.js": "vendor/MagnificPopup/jquery.magnific-popup.min.ba6cf724c8bb.js", "vendor/MagnificPopup/magnific-popup.css": "vendor/MagnificPopup/magnific-popup.30b593b71d76.css", "vendor/parallax100/parallax100.js": "vendor/parallax100/parallax100.e55f18c0d62d.js", "vendor/perfect-scrollbar/perfect-scrollbar.css": "vendor/perfect-scrollbar/perfect-scrollbar.31498c7baf7a.css", "vendor/perfect-scrollbar/perfect-scrollbar.min.js": "vendor/perfect-scrollbar/perfect-scrollbar.min.d6395960abdc.js", "vendor/select2/select2.css": "vendor/select2/select2.b38fc0c28779.css", "vendor/select2/select2.js": "vendor/select2/select2.a31b67a879ae.js", "vendor/select2/select2.min.css": "vendor/select2/select2.min.d44571114a90.css", "vendor/select2/select2.min.js": "vendor/select2/select2.min.e87ca4c3554f.js", "vendor/slick/ajax-loader.gif": "vendor\\slick\\ajax-loader.c5cd7f530057.gif", "vendor/slick/config.rb": "vendor\\slick\\config.c47857bcaf2a.rb", "vendor/slick/slick-theme.css": "vendor/slick/slick-theme.590ee7f4d13f.css", "vendor/slick/slick-theme.less": "vendor\\slick\\slick-theme.c7c46d596084.less", "vendor/slick/slick-theme.scss": "vendor\\slick\\slick-theme.e97dc549d545.scss", "vendor/slick/slick.css": "vendor/slick/slick.f38b2db10e01.css", "vendor/slick/slick.js": "vendor/slick/slick.da910267cd96.js", "vendor/slick/slick.less": "vendor\\slick\\slick.f5309cf69051.less", "vendor/slick/slick.min.js": "vendor/slick/slick.min.d5a61c749e44.js", "vendor/slick/slick.scss": "vendor\\slick\\slick.f5309cf69051.scss", "vendor/sweetalert/sweetalert.min.js": "vendor/sweetalert/sweetalert.min.03d846cf1a55.js", "admin/css/autocomplete.css": "admin/css/autocomplete.4a81fc4242d0.css", "admin/css/base.css": "admin/css/base.1f418065fc2c.css", "admin/css/changelists.css": "admin/css/changelists.cd4dd90ae1a1.css", "admin/css/dashboard.css": "admin/css/dashboard.be83f13e4369.css", "admin/css/fonts.css": "admin/css/fonts.168bab448fee.css", "admin/css/forms.css": "admin/css/forms.332ab41432e2.css", "admin/css/login.css": "admin/css/login.8b76a9f7cbf6.css", "admin/css/nav_sidebar.css": "admin/css/nav_sidebar.e32d345464bd.css", "admin/css/responsive.css": "admin/css/responsive.b9e1565b3609.css", "admin/css/responsive_rtl.css": "admin/css/responsive_rtl.e13ae754cceb.css", "admin/css/rtl.css": "admin/css/rtl.4bc23eb90919.css", "admin/css/widgets.css": "admin/css/widgets.694d845b2cb1.css", "admin/fonts/LICENSE.txt": "admin\\fonts\\LICENSE.d273d63619c9.txt", "admin/fonts/README.txt": "admin\\fonts\\README.ab99e6b541ea.txt", "admin/fonts/Roboto-Bold-webfont.woff": "admin\\fonts\\Roboto-Bold-webfont.50d75e48e0a3.woff", "admin/fonts/Roboto-Light-webfont.woff": "admin\\fonts\\Roboto-Light-webfont.c73eb1ceba33.woff", "admin/fonts/Roboto-Regular-webfont.woff": "admin\\fonts\\Roboto-Regular-webfont.35b07eb2f871.woff", "admin/img/calendar-icons.svg": "admin\\img\\calendar-icons.39b290681a8b.svg", "admin/img/icon-addlink.svg": "admin\\img\\icon-addlink.d519b3bab011.svg", "admin/img/icon-alert.svg": "admin\\img\\icon-alert.034cc7d8a67f.svg", "admin/img/icon-calendar.svg": "admin\\img\\icon-calendar.ac7aea671bea.svg", "admin/img/icon-changelink.svg": "admin\\img\\icon-changelink.18d2fd706348.svg", "admin/img/icon-clock.svg": "admin\\img\\icon-clock.e1d4dfac3f2b.svg", "admin/img/icon-deletelink.svg": "admin\\img\\icon-deletelink.564ef9dc3854.svg", "admin/img/icon-no.svg": "admin\\img\\icon-no.439e821418cd.svg", "admin/img/icon-unknown-alt.svg": "admin\\img\\icon-unknown-alt.81536e128bb6.svg", "admin/img/icon-unknown.svg": "admin\\img\\icon-unknown.a18cb4398978.svg", "admin/img/icon-viewlink.svg": "admin\\img\\icon-viewlink.41eb31f7826e.svg", "admin/img/icon-yes.svg": "admin\\img\\icon-yes.d2f9f035226a.svg", "admin/img/inline-delete.svg": "admin\\img\\inline-delete.fec1b761f254.svg", "admin/img/LICENSE": "admin\\img\\LICENSE.2c54f4e1ca1c", "admin/img/README.txt": "admin\\img\\README.a70711a38d87.txt", "admin/img/search.svg": "admin\\img\\search.7cf54ff789c6.svg", "admin/img/selector-icons.svg": "admin\\img\\selector-icons.b4555096cea2.svg", "admin/img/sorting-icons.svg": "admin\\img\\sorting-icons.3a097b59f104.svg", "admin/img/tooltag-add.svg": "admin\\img\\tooltag-add.e59d620a9742.svg", "admin/img/tooltag-arrowright.svg": "admin\\img\\tooltag-arrowright.bbfb788a849e.svg", "admin/js/actions.js": "admin/js/actions.eac7e3441574.js", "admin/js/autocomplete.js": "admin/js/autocomplete.c508b167ab61.js", "admin/js/calendar.js": "admin/js/calendar.f8a5d055eb33.js", "admin/js/cancel.js": "admin/js/cancel.ecc4c5ca7b32.js", "admin/js/change_form.js": "admin/js/change_form.9d8ca4f96b75.js", "admin/js/collapse.js": "admin/js/collapse.f84e7410290f.js", "admin/js/core.js": "admin/js/core.5d6b384a08b5.js", "admin/js/inlines.js": "admin/js/inlines.fb1617228dbe.js", "admin/js/jquery.init.js": "admin/js/jquery.init.b7781a0897fc.js", "admin/js/nav_sidebar.js": "admin/js/nav_sidebar.3535caba9444.js", "admin/js/popup_response.js": "admin/js/popup_response.c6cc78ea5551.js", "admin/js/prepopulate.js": "admin/js/prepopulate.bd2361dfd64d.js", "admin/js/prepopulate_init.js": "admin/js/prepopulate_init.e056047b7a7e.js", "admin/js/SelectBox.js": "admin/js/SelectBox.8161741c7647.js", "admin/js/SelectFilter2.js": "admin/js/SelectFilter2.d250dcb52a9a.js", "admin/js/urlify.js": "admin/js/urlify.25cc3eac8123.js", "img/curved-images/curved-10.jpg": "img\\curved-images\\curved-10.2c5338a8dd20.jpg", "img/curved-images/curved-11.jpg": "img\\curved-images\\curved-11.0fa4f59277e8.jpg", "img/curved-images/curved-6.jpg": "img\\curved-images\\curved-6.1ba3792d51e1.jpg", "img/curved-images/curved-8.jpg": "img\\curved-images\\curved-8.f053150f8603.jpg", "img/curved-images/curved0.jpg": "img\\curved-images\\curved0.ae4b6c43f25c.jpg", "img/curved-images/curved1.jpg": "img\\curved-images\\curved1.06bfaf1f8c87.jpg", "img/curved-images/curved10.jpg": "img\\curved-images\\curved10.cf37b5ad041d.jpg", "img/curved-images/curved11-small.jpg": "img\\curved-images\\curved11-small.ef71b92b97a2.jpg", "img/curved-images/curved11.jpg": "img\\curved-images\\curved11.0bd5b3f51f9f.jpg", "img/curved-images/curved12.jpg": "img\\curved-images\\curved12.768447b829c8.jpg", "img/curved-images/curved13.jpg": "img\\curved-images\\curved13.a40f4ca92b48.jpg", "img/curved-images/curved14.jpg": "img\\curved-images\\curved14.34ecccd6c3df.jpg", "img/curved-images/curved19.jpg": "img\\curved-images\\curved19.f73876055853.jpg", "img/curved-images/curved2.jpg": "img\\curved-images\\curved2.2dc103cbd6f0.jpg", "img/curved-images/curved21.jpg": "img\\curved-images\\curved21.54d3b73a144d.jpg", "img/curved-images/curved3.jpg": "img\\curved-images\\curved3.e9278be58b0c.jpg", "img/curved-images/curved4.jpg": "img\\curved-images\\curved4.1da9530986da.jpg", "img/curved-images/curved5-small.jpg": "img\\curved-images\\curved5-small.c7a1c8b039e5.jpg", "img/curved-images/curved5.jpg": "img\\curved-images\\curved5.bbfb7d98e679.jpg", "img/curved-images/curved6-small.jpg": "img\\curved-images\\curved6-small.5dd5d6ce9162.jpg", "img/curved-images/curved6.jpg": "img\\curved-images\\curved6.b31b3715c5f9.jpg", "img/curved-images/curved7.jpg": "img\\curved-images\\curved7.32fb09df454f.jpg", "img/curved-images/curved8.jpg": "img\\curved-images\\curved8.2e986c7d60e5.jpg", "img/curved-images/curved9.jpg": "img\\curved-images\\curved9.b94cc6935a3a.jpg", "img/curved-images/white-curved.jpeg": "img\\curved-images\\white-curved.4dc196db0cfc.jpeg", "img/illustrations/icon-documentation.svg": "img\\illustrations\\icon-documentation.8429eb8164a6.svg", "img/illustrations/rocket-white.png": "img\\illustrations\\rocket-white.d7c8fd14002e.png", "img/logos/mastercard.png": "img\\logos\\mastercard.e1efc6004923.png", "img/logos/visa.png": "img\\logos\\visa.98edc46df132.png", "img/shapes/pattern-lines.svg": "img\\shapes\\pattern-lines.920849439668.svg", "img/shapes/shape-1.svg": "img\\shapes\\shape-1.8fc755aed67f.svg", "img/shapes/shape-2.svg": "img\\shapes\\shape-2.8291a78147e1.svg", "img/shapes/shape-3.svg": "img\\shapes\\shape-3.d7e9bb11cdfe.svg", "img/shapes/wave-down.svg": "img\\shapes\\wave-down.38cbf82221b7.svg", "img/shapes/wave-up.svg": "img\\shapes\\wave-up.818d83be4be0.svg", "img/shapes/waves-gray.svg": "img\\shapes\\waves-gray.598047d93760.svg", "img/shapes/waves-white.svg": "img\\shapes\\waves-white.634c6eb9fa50.svg", "img/small-logos/icon-sun-cloud.png": "img\\small-logos\\icon-sun-cloud.83766986a3e1.png", "img/small-logos/logo-atlassian.svg": "img\\small-logos\\logo-atlassian.3dc0055972d6.svg", "img/small-logos/logo-invision.svg": "img\\small-logos\\logo-invision.4731441a6ff1.svg", "img/small-logos/logo-jira.svg": "img\\small-logos\\logo-jira.cb154bf24a4d.svg", "img/small-logos/logo-slack.svg": "img\\small-logos\\logo-slack.9a05c08ac513.svg", "img/small-logos/logo-spotify.svg": "img\\small-logos\\logo-spotify.b0a5df30d111.svg", "img/small-logos/logo-webdev.svg": "img\\small-logos\\logo-webdev.4f0b3513c3b1.svg", "img/small-logos/logo-xd.svg": "img\\small-logos\\logo-xd.c0c969935d58.svg", "img/theme/angular.jpg": "img\\theme\\angular.368685db949c.jpg", "img/theme/bootstrap.jpg": "img\\theme\\bootstrap.ab904daa5489.jpg", "img/theme/dribbble.png": "img\\theme\\dribbble.ed2ced817771.png", "img/theme/dropbox.png": "img\\theme\\dropbox.759c287fc60e.png", "img/theme/mastercard.png": "img\\theme\\mastercard.5481775d9454.png", "img/theme/paypal.png": "img\\theme\\paypal.efc2d12a0361.png", "img/theme/react.jpg": "img\\theme\\react.c4eb3d0be0cf.jpg", "img/theme/sketch.jpg": "img\\theme\\sketch.e7c82e5c569d.jpg", "img/theme/slack.png": "img\\theme\\slack.8c62b7c5bfdc.png", "img/theme/spotify.jpeg": "img\\theme\\spotify.7d82b526cdc0.jpeg", "img/theme/tim.png": "img\\theme\\tim.b23d4d826115.png", "img/theme/unass.jpg": "img\\theme\\unass.0d1070690ef8.jpg", "img/theme/visa.png": "img\\theme\\visa.869161b27aaf.png", "img/theme/vue.jpg": "img\\theme\\vue.9378e368a757.jpg", "js/core/bootstrap.bundle.min.js": "js/core/bootstrap.bundle.min.dfd824922bdc.js", "js/core/bootstrap.min.js": "js/core/bootstrap.min.f10726529d0b.js", "js/core/popper.min.js": "js/core/popper.min.053e47d2e858.js", "js/plugins/bootstrap-notify.js": "js/plugins/bootstrap-notify.21e771df8c43.js", "js/plugins/Chart.extension.js": "js/plugins/Chart.extension.5e5078409e28.js", "js/plugins/chartjs.min.js": "js/plugins/chartjs.min.50167bab4589.js", "js/plugins/perfect-scrollbar.min.js": "js/plugins/perfect-scrollbar.min.7726dbb47415.js", "js/plugins/smooth-scrollbar.min.js": "js/plugins/smooth-scrollbar.min.eeec495792b7.js", "scss/argon-dashboard/theme.scss": "scss\\argon-dashboard\\theme.6f483da817b4.scss", "scss/argon-dashboard/_alert.scss": "scss\\argon-dashboard\\_alert.680e289fa92a.scss", "scss/argon-dashboard/_avatars.scss": "scss\\argon-dashboard\\_avatars.791e98aac044.scss", "scss/argon-dashboard/_badge.scss": "scss\\argon-dashboard\\_badge.7d409a765a1f.scss", "scss/argon-dashboard/_breadcrumbs.scss": "scss\\argon-dashboard\\_breadcrumbs.a37d6afdd36f.scss", "scss/argon-dashboard/_buttons.scss": "scss\\argon-dashboard\\_buttons.7251835e9623.scss", "scss/argon-dashboard/_cards.scss": "scss\\argon-dashboard\\_cards.49d60835fe95.scss", "scss/argon-dashboard/_dark-version.scss": "scss\\argon-dashboard\\_dark-version.c8182ef9af52.scss", "scss/argon-dashboard/_dropdown.scss": "scss\\argon-dashboard\\_dropdown.2aff41184416.scss", "scss/argon-dashboard/_dropup.scss": "scss\\argon-dashboard\\_dropup.fdb904f2c897.scss", "scss/argon-dashboard/_fixed-plugin.scss": "scss\\argon-dashboard\\_fixed-plugin.47e499d73ee5.scss", "scss/argon-dashboard/_footer.scss": "scss\\argon-dashboard\\_footer.0e294a5bacbb.scss", "scss/argon-dashboard/_forms.scss": "scss\\argon-dashboard\\_forms.f6cbb2a41e02.scss", "scss/argon-dashboard/_gradients.scss": "scss\\argon-dashboard\\_gradients.89e300e98026.scss", "scss/argon-dashboard/_header.scss": "scss\\argon-dashboard\\_header.91ac82f60b1b.scss", "scss/argon-dashboard/_info-areas.scss": "scss\\argon-dashboard\\_info-areas.aaadf566cbb2.scss", "scss/argon-dashboard/_misc.scss": "scss\\argon-dashboard\\_misc.19c538fe5f5e.scss", "scss/argon-dashboard/_nav.scss": "scss\\argon-dashboard\\_nav.bf1f97166142.scss", "scss/argon-dashboard/_navbar-vertical.scss": "scss\\argon-dashboard\\_navbar-vertical.1a97ac28d2af.scss", "scss/argon-dashboard/_navbar.scss": "scss\\argon-dashboard\\_navbar.fd5beedcfae3.scss", "scss/argon-dashboard/_pagination.scss": "scss\\argon-dashboard\\_pagination.13115ef9291e.scss", "scss/argon-dashboard/_popovers.scss": "scss\\argon-dashboard\\_popovers.4e2a5e161272.scss", "scss/argon-dashboard/_progress.scss": "scss\\argon-dashboard\\_progress.624cd1e63aea.scss", "scss/argon-dashboard/_rtl.scss": "scss\\argon-dashboard\\_rtl.62d475bacabd.scss", "scss/argon-dashboard/_social-buttons.scss": "scss\\argon-dashboard\\_social-buttons.107b7fc7beac.scss", "scss/argon-dashboard/_tables.scss": "scss\\argon-dashboard\\_tables.b1f7541a868d.scss", "scss/argon-dashboard/_tilt.scss": "scss\\argon-dashboard\\_tilt.beccf2556a29.scss", "scss/argon-dashboard/_timeline.scss": "scss\\argon-dashboard\\_timeline.3f051c74a055.scss", "scss/argon-dashboard/_tooltips.scss": "scss\\argon-dashboard\\_tooltips.12ad2a6121ac.scss", "scss/argon-dashboard/_typography.scss": "scss\\argon-dashboard\\_typography.6c33abf76281.scss", "scss/argon-dashboard/_utilities-extend.scss": "scss\\argon-dashboard\\_utilities-extend.21b0282ab373.scss", "scss/argon-dashboard/_utilities.scss": "scss\\argon-dashboard\\_utilities.a1a268e541d7.scss", "scss/argon-dashboard/_variables.scss": "scss\\argon-dashboard\\_variables.5f4f63464bc1.scss", "css/login.css": "css/login.73c3dcafb273.css", "css/main.css": "css/main.a85520671cac.css", "css/register.css": "css/register.3354f65a3b3c.css", "css/util.css": "css/util.167b4807c6c5.css", "images/about-01.jpg": "images\\about-01.1d7b722d0f3c.jpg", "images/about-02.jpg": "images\\about-02.6a6ce6be7293.jpg", "images/avatar-01.jpg": "images\\avatar-01.5383a8829465.jpg", "images/ban1.webp": "images\\ban1.cb08353096b2.webp", "images/ban2.webp": "images\\ban2.612b5f72ce5a.webp", "images/ban3.webp": "images\\ban3.5b28b65359a7.webp", "images/ban4.jpg": "images\\ban4.5889fad2c24d.jpg", "images/ban5.jpg": "images\\ban5.3950c5bc1d04.jpg", "images/ban6.jpg": "images\\ban6.8433927d1c0e.jpg", "images/banner-01.jpg": "images\\banner-01.3df552912ddd.jpg", "images/banner-02.jpg": "images\\banner-02.e0d0afc54b12.jpg", "images/banner-03.jpg": "images\\banner-03.be26d1c4488f.jpg", "images/banner-04.jpg": "images\\banner-04.2be12b724dde.jpg", "images/banner-05.jpg": "images\\banner-05.6b0dbd4d08a5.jpg", "images/banner-06.jpg": "images\\banner-06.a9ff0f886ff1.jpg", "images/banner-07.jpg": "images\\banner-07.efb3cb279026.jpg", "images/banner-08.jpg": "images\\banner-08.a9e0640a6be3.jpg", "images/banner-09.jpg": "images\\banner-09.fe53e5a26d4b.jpg", "images/bbgg.jpg": "images\\bbgg.48aeb41585e7.jpg", "images/bg-01.jpg": "images\\bg-01.a4c7c8b1e2ed.jpg", "images/bg-02.jpg": "images\\bg-02.991489d49310.jpg", "images/blog-01.jpg": "images\\blog-01.fb2ef6034430.jpg", "images/blog-02.jpg": "images\\blog-02.ec8a1dc1b66c.jpg", "images/blog-03.jpg": "images\\blog-03.ef2c1f203ff2.jpg", "images/blog-04.jpg": "images\\blog-04.e3bd41dd22ca.jpg", "images/blog-05.jpg": "images\\blog-05.64d77436bae1.jpg", "images/blog-06.jpg": "images\\blog-06.19b5a79da2d2.jpg", "images/checked.png": "images\\checked.da188ccb78f1.png", "images/gallery-01.jpg": "images\\gallery-01.8fe02bb3ac47.jpg", "images/gallery-02.jpg": "images\\gallery-02.594d01faa9a8.jpg", "images/gallery-03.jpg": "images\\gallery-03.1ee9c08288a3.jpg", "images/gallery-04.jpg": "images\\gallery-04.40e63119d721.jpg", "images/gallery-05.jpg": "images\\gallery-05.dbfe9e6792ad.jpg", "images/gallery-06.jpg": "images\\gallery-06.8caf9012a991.jpg", "images/gallery-07.jpg": "images\\gallery-07.90b6aa060797.jpg", "images/gallery-08.jpg": "images\\gallery-08.ccedadd94f8c.jpg", "images/gallery-09.jpg": "images\\gallery-09.9fe90bb01456.jpg", "images/item-cart-01.jpg": "images\\item-cart-01.831feb663c4d.jpg", "images/item-cart-02.jpg": "images\\item-cart-02.d9851d11e638.jpg", "images/item-cart-03.jpg": "images\\item-cart-03.d470cd3e5e42.jpg", "images/item-cart-04.jpg": "images\\item-cart-04.57a06326fdb2.jpg", "images/item-cart-05.jpg": "images\\item-cart-05.559be58de4c6.jpg", "images/l1.png": "images\\l1.dd1340cba933.png", "images/l2.png": "images\\l2.cb0b3ebead19.png", "images/logo-whatsapp-png-46041.png": "images\\logo-whatsapp-png-46041.96d49fa98516.png", "images/product-01.jpg": "images\\product-01.54ca4230f9ae.jpg", "images/product-02.jpg": "images\\product-02.5da023aab491.jpg", "images/product-03.jpg": "images\\product-03.c4e2b18ba96b.jpg", "images/product-04.jpg": "images\\product-04.7dcf70064c06.jpg", "images/product-05.jpg": "images\\product-05.d34f9c47de8a.jpg", "images/product-06.jpg": "images\\product-06.8fd2852121ee.jpg", "images/product-07.jpg": "images\\product-07.0a482ea846f8.jpg", "images/product-08.jpg": "images\\product-08.fa0b2277f00e.jpg", "images/product-09.jpg": "images\\product-09.a51376c023a2.jpg", "images/product-10.jpg": "images\\product-10.8514436597fa.jpg", "images/product-11.jpg": "images\\product-11.2733a2e5e937.jpg", "images/product-12.jpg": "images\\product-12.38a1864be4b2.jpg", "images/product-13.jpg": "images\\product-13.5288e69a4fd4.jpg", "images/product-14.jpg": "images\\product-14.3bdaf680e3b9.jpg", "images/product-15.jpg": "images\\product-15.662ce7827387.jpg", "images/product-16.jpg": "images\\product-16.42f5693f89e5.jpg", "images/product-detail-01.jpg": "images\\product-detail-01.014e05baf2b1.jpg", "images/product-detail-02.jpg": "images\\product-detail-02.8ef42b7c4afe.jpg", "images/product-detail-03.jpg": "images\\product-detail-03.3d84c0265bce.jpg", "images/product-min-01.jpg": "images\\product-min-01.8a433bcc9956.jpg", "images/product-min-02.jpg": "images\\product-min-02.1611205705fb.jpg", "images/product-min-03.jpg": "images\\product-min-03.e27f93d09b78.jpg", "images/slide-01.jpg": "images\\slide-01.e13871339ff5.jpg", "images/slide-02.jpg": "images\\slide-02.e4498020dff8.jpg", "images/slide-03.jpg": "images\\slide-03.dbde8791ba5b.jpg", "images/slide-04.jpg": "images\\slide-04.850ced5ad65d.jpg", "images/slide-05.jpg": "images\\slide-05.900bb75efea9.jpg", "images/slide-06.jpg": "images\\slide-06.f2f67b25c83b.jpg", "images/slide-07.jpg": "images\\slide-07.5b9bcd24e9ee.jpg", "images/thumb-01.jpg": "images\\thumb-01.cf6681af313e.jpg", "images/thumb-02.jpg": "images\\thumb-02.7750ab5f64e5.jpg", "images/thumb-03.jpg": "images\\thumb-03.ef6b7c4a3416.jpg", "js/checkout.js": "js/checkout.39bf745705c9.js", "js/custom.js": "js/custom.2c1cccef7fd6.js", "js/jquery-3.6.0.min.js": "js/jquery-3.6.0.min.3e4bb227fb55.js", "js/main.js": "js/main.8baeca2245a9.js", "js/map-custom.js": "js/map-custom.7fa8338b33b6.js", "js/slick-custom.js": "js/slick-custom.6e6a288a7cb7.js", "css/argon-dashboard.css": "css/argon-dashboard.dac8a539991c.css", "css/argon-dashboard.css.map": "css\\argon-dashboard.css.99795cc1be2f.map", "css/argon-dashboard.min.css": "css/argon-dashboard.min.4a9d060a08e2.css", "css/nucleo-icons.css": "css/nucleo-icons.1297ae7692c0.css", "css/nucleo-svg.css": "css/nucleo-svg.99515a64208b.css", "fonts/nucleo-icons.eot": "fonts\\nucleo-icons.c1733565b32b.eot", "fonts/nucleo-icons.svg": "fonts\\nucleo-icons.0b8a30b10cbe.svg", "fonts/nucleo-icons.ttf": "fonts\\nucleo-icons.f82ec6ba2dc4.ttf", "fonts/nucleo-icons.woff": "fonts\\nucleo-icons.2569aaea6eaa.woff", "fonts/nucleo-icons.woff2": "fonts\\nucleo-icons.426439788ec5.woff2", "fonts/nucleo.eot": "fonts\\nucleo.03ef1918e505.eot", "fonts/nucleo.ttf": "fonts\\nucleo.b17a118e13e5.ttf", "fonts/nucleo.woff": "fonts\\nucleo.f0b489a5dbbf.woff", "fonts/nucleo.woff2": "fonts\\nucleo.5987dd12fea7.woff2", "img/apple-icon.png": "img\\apple-icon.0a15dfd6563b.png", "img/bg-profile.jpg": "img\\bg-profile.9af971bfd31f.jpg", "img/bg1.jpg": "img\\bg1.f2646f553c9e.jpg", "img/bruce-mars.jpg": "img\\bruce-mars.c0421fd9d963.jpg", "img/carousel-1.jpg": "img\\carousel-1.7a177f3491aa.jpg", "img/carousel-2.jpg": "img\\carousel-2.a3b2abe8e787.jpg", "img/carousel-3.jpg": "img\\carousel-3.54bc08f94e03.jpg", "img/down-arrow-dark.svg": "img\\down-arrow-dark.1bf60cafd50e.svg", "img/down-arrow-white.svg": "img\\down-arrow-white.157f6258448d.svg", "img/down-arrow.svg": "img\\down-arrow.99340c47c9ec.svg", "img/favicon.png": "img\\favicon.0a15dfd6563b.png", "img/home-decor-1.jpg": "img\\home-decor-1.decbdadf95d8.jpg", "img/home-decor-2.jpg": "img\\home-decor-2.249f600cbd97.jpg", "img/home-decor-3.jpg": "img\\home-decor-3.2d98a7aa0729.jpg", "img/ivana-square.jpg": "img\\ivana-square.a7842ce3f1ac.jpg", "img/ivancik.jpg": "img\\ivancik.8799a9d67bf7.jpg", "img/kal-visuals-square.jpg": "img\\kal-visuals-square.83531691976d.jpg", "img/logo-ct-dark.png": "img\\logo-ct-dark.cd73ca3b99a8.png", "img/logo-ct.png": "img\\logo-ct.11e796dceef4.png", "img/marie.jpg": "img\\marie.94384a47e4cf.jpg", "img/team-1.jpg": "img\\team-1.66f62826f5ee.jpg", "img/team-2.jpg": "img\\team-2.de26a134af67.jpg", "img/team-3.jpg": "img\\team-3.08ced048debb.jpg", "img/team-4.jpg": "img\\team-4.897617b8a2f5.jpg", "img/vr-bg.jpg": "img\\vr-bg.f242b8f06a98.jpg", "js/argon-dashboard.js": "js/argon-dashboard.b61536e3a431.js", "js/argon-dashboard.js.map": "js\\argon-dashboard.js.6a71388b5136.map", "js/argon-dashboard.min.js": "js/argon-dashboard.min.8a8b93cd559f.js", "js/chart.js": "js/chart.a8827e147b69.js", "scss/argon-dashboard.scss": "scss/argon-dashboard.e75210534869.scss"}, "version": "1.0"}